LICENSE
MANIFEST.in
README.md
setup.cfg
setup.py
cctek/__init__.py
cctek/cardchecker.py
cctek/commands.py
cctek/dataloader.py
cctek/magnet.py
cctek/data/all_files.yml
cctek/data/0/0196.yml
cctek/data/0/0215.yml
cctek/data/0/0424.yml
cctek/data/0/0571.yml
cctek/data/1/1030.yml
cctek/data/1/1111.yml
cctek/data/1/1113.yml
cctek/data/1/1119.yml
cctek/data/1/1310.yml
cctek/data/1/1800.yml
cctek/data/1/1988.yml
cctek/data/2/2131.yml
cctek/data/2/2215.yml
cctek/data/2/2632.yml
cctek/data/2/2670.yml
cctek/data/2/2724.yml
cctek/data/3/3000.yml
cctek/data/3/3001.yml
cctek/data/3/3002.yml
cctek/data/3/3003.yml
cctek/data/3/3004.yml
cctek/data/3/3005.yml
cctek/data/3/3006.yml
cctek/data/3/3007.yml
cctek/data/3/3008.yml
cctek/data/3/3009.yml
cctek/data/3/3010.yml
cctek/data/3/3011.yml
cctek/data/3/3012.yml
cctek/data/3/3013.yml
cctek/data/3/3014.yml
cctek/data/3/3015.yml
cctek/data/3/3016.yml
cctek/data/3/3017.yml
cctek/data/3/3018.yml
cctek/data/3/3019.yml
cctek/data/3/3020.yml
cctek/data/3/3021.yml
cctek/data/3/3022.yml
cctek/data/3/3023.yml
cctek/data/3/3024.yml
cctek/data/3/3025.yml
cctek/data/3/3026.yml
cctek/data/3/3027.yml
cctek/data/3/3028.yml
cctek/data/3/3029.yml
cctek/data/3/3030.yml
cctek/data/3/3031.yml
cctek/data/3/3032.yml
cctek/data/3/3033.yml
cctek/data/3/3034.yml
cctek/data/3/3035.yml
cctek/data/3/3036.yml
cctek/data/3/3037.yml
cctek/data/3/3038.yml
cctek/data/3/3039.yml
cctek/data/3/3040.yml
cctek/data/3/3041.yml
cctek/data/3/3042.yml
cctek/data/3/3043.yml
cctek/data/3/3044.yml
cctek/data/3/3045.yml
cctek/data/3/3046.yml
cctek/data/3/3047.yml
cctek/data/3/3048.yml
cctek/data/3/3049.yml
cctek/data/3/3050.yml
cctek/data/3/3051.yml
cctek/data/3/3052.yml
cctek/data/3/3053.yml
cctek/data/3/3054.yml
cctek/data/3/3055.yml
cctek/data/3/3056.yml
cctek/data/3/3057.yml
cctek/data/3/3058.yml
cctek/data/3/3059.yml
cctek/data/3/3089.yml
cctek/data/3/3095.yml
cctek/data/3/3110.yml
cctek/data/3/3199.yml
cctek/data/3/3240.yml
cctek/data/3/3379.yml
cctek/data/3/3400.yml
pycctek.egg-info/PKG-INFO
pycctek.egg-info/SOURCES.txt
pycctek.egg-info/dependency_links.txt
pycctek.egg-info/entry_points.txt
pycctek.egg-info/requires.txt
pycctek.egg-info/top_level.txt