Metadata-Version: 2.1
Name: pycctek
Version: 0.0.7
Summary: "Issuer Identification Number Database and Verification Utility Library. Luhn Algorithm, BIN Checker, Random Credit Card Generators."
Home-page: https://github.com/TralahM/pycctek
Author: Tralah M Brian
Author-email: musyoki.brian@tralahtek.com
Maintainer: Tralah M Brian
Maintainer-email: musyoki.brian@tralahtek.com
License: GPLv3
Keywords: development,credit_cards,database,finance
Platform: UNKNOWN
Classifier: Development Status :: 4 - Beta
Classifier: Intended Audience :: Developers
Classifier: Topic :: Software Development :: Build Tools
Classifier: Topic :: Database
Classifier: Topic :: Software Development :: Libraries
Classifier: Topic :: System :: Shells
Classifier: Topic :: Utilities
Classifier: License :: OSI Approved :: GNU General Public License v3 (GPLv3)
Classifier: Natural Language :: English
Classifier: Programming Language :: Python :: 2
Classifier: Programming Language :: Python :: 2.6
Classifier: Programming Language :: Python :: 2.7
Classifier: Programming Language :: Python :: 3
Classifier: Programming Language :: Python :: 3.2
Classifier: Programming Language :: Python :: 3.3
Classifier: Programming Language :: Python :: 3.4
Classifier: Programming Language :: Python :: 3.5
Classifier: Programming Language :: Python :: 3.6
Classifier: Programming Language :: Python :: 3.7
Classifier: Programming Language :: Python :: 3.8
Classifier: Operating System :: Unix
